{"sections":{"skin-journeys-hero":{"type":"skin-journeys-hero","blocks":{"6d2d93ff-7847-4e56-aac5-b369bb04d948":{"type":"slides","settings":{"featured_article":"diaries\/matthews-skin-diary","button-label":"Watch Now","featured_article_video":"https:\/\/vimeo.com\/715804083","featured_article_image":"shopify:\/\/shop_images\/1442549622-6ec31fcf44fe7d8509ddb6a955693d8c7b302facce086ac9a9abb691130ffec8-d.jpg","featured_article_title":"Bri's Acne Journey"}},"916bd4a9-bc09-412d-835b-e2b44830e21f":{"type":"slides","settings":{"featured_article":"diaries\/article-stories-6","button-label":"Watch Now","featured_article_video":"https:\/\/vimeo.com\/738069340","featured_article_image":"shopify:\/\/shop_images\/1485195169-908e307f6a1757be8c06a12efae56e70d3d506544a0c4cb640f4b882244cfad4-d.jpg","featured_article_title":"Couple Goals"}},"a414a27e-676a-469e-973f-af1b250aea24":{"type":"slides","settings":{"featured_article":"diaries\/blues-skin-diary","button-label":"Watch Now","featured_article_video":"https:\/\/vimeo.com\/738070012","featured_article_image":"shopify:\/\/shop_images\/chelsea.jpg","featured_article_title":"Chelsea Tries The Spot Treatment"}}},"block_order":["6d2d93ff-7847-4e56-aac5-b369bb04d948","916bd4a9-bc09-412d-835b-e2b44830e21f","a414a27e-676a-469e-973f-af1b250aea24"],"settings":{"background-image":"shopify:\/\/shop_images\/Mask_Group_140ad5bb-50d5-4c6e-87c0-1a51c6f6ce51.png","pretitle":"","title":"SKIN DIARIES","text":"At The Skin Shark we're all about real people and real results. Checkout the testimonials & stories from our amazing community of #SkinSharkSkinfluencers who have tried our products themselves.","diariesBlog":"diaries"}},"1642039809721a7302":{"type":"title-and-articles","blocks":{"2d785077-4788-43fd-bc7a-7c13653e4ae8":{"type":"social-videos","disabled":true,"settings":{"social-video-image":"shopify:\/\/shop_images\/Screen_Shot_2022-06-01_at_9.53.09_am.png","social-video-link":"https:\/\/vimeo.com\/715804083","social-video-pretitle":"THE SKIN SHARK","social-video-title":"Bri's Acne Journey","social-video-author":"Bri"}},"70c92550-3879-470f-95e4-f6f1168e2187":{"type":"social-videos","disabled":true,"settings":{"social-video-image":"shopify:\/\/shop_images\/Screen_Shot_2022-08-10_at_8.32.54_am.png","social-video-link":"https:\/\/vimeo.com\/738069340","social-video-pretitle":"The Skin Shark","social-video-title":"Couple Goals","social-video-author":"Sydney"}},"d90ee8eb-88a0-41b3-b908-c420280a7212":{"type":"social-videos","disabled":true,"settings":{"social-video-image":"shopify:\/\/shop_images\/Screen_Shot_2022-08-10_at_8.33.45_am.png","social-video-link":"https:\/\/vimeo.com\/738070012","social-video-pretitle":"The Skin Shark","social-video-title":"Chelsea tries The Spot Treatment","social-video-author":"Chelsea"}},"870894ce-7b0c-4d36-aff6-52ac4ddee004":{"type":"social-videos","settings":{"social-video-image":"shopify:\/\/shop_images\/Screen_Shot_2022-08-10_at_8.33.34_am.png","social-video-link":"https:\/\/vimeo.com\/738069895","social-video-pretitle":"The Skin Shark","social-video-title":"Wil seeing fast results","social-video-author":"@fackwil"}},"92168691-ffec-43bf-958d-40c27a47af4f":{"type":"social-videos","settings":{"social-video-image":"shopify:\/\/shop_images\/Screen_Shot_2022-08-10_at_8.31.55_am.png","social-video-link":"https:\/\/vimeo.com\/738070178","social-video-pretitle":"The Skin Shark","social-video-title":"Drea's Success With Spots","social-video-author":"Drea"}},"022560b9-c005-486c-ae22-154d51f9d254":{"type":"social-videos","settings":{"social-video-image":"shopify:\/\/shop_images\/Screen_Shot_2022-06-01_at_9.57.11_am.png","social-video-link":"https:\/\/vimeo.com\/715803690","social-video-pretitle":"","social-video-title":"Samira's 6 Week Journey","social-video-author":"Samira"}},"1a8eb817-bfbb-4073-9e0f-9a5ad980ca10":{"type":"social-videos","settings":{"social-video-image":"shopify:\/\/shop_images\/Screen_Shot_2022-06-01_at_9.58.59_am.png","social-video-link":"https:\/\/vimeo.com\/715803889","social-video-pretitle":"","social-video-title":"Kaytlyn's Spot Treatment Results","social-video-author":"Kaytlyn"}},"25aeb6e6-c548-44b3-a173-d14f970911a5":{"type":"social-videos","settings":{"social-video-image":"shopify:\/\/shop_images\/Screen_Shot_2022-08-10_at_8.32.29_am.png","social-video-link":"https:\/\/vimeo.com\/738069939","social-video-pretitle":"The Skin Shark","social-video-title":"Spot Treatment Before & After","social-video-author":"Bri"}},"71a3f523-5614-4533-b42a-3eed440d3fe5":{"type":"social-videos","settings":{"social-video-image":"shopify:\/\/shop_images\/Screen_Shot_2022-08-10_at_8.31.34_am.png","social-video-link":"https:\/\/vimeo.com\/738070407","social-video-pretitle":"The Skin Shark","social-video-title":"Talliyah is Skin Positive with The Skin Shark","social-video-author":"Talliyah"}},"ca97e3eb-d899-4613-a2c1-fdbfcf1e15bc":{"type":"social-videos","settings":{"social-video-image":"shopify:\/\/shop_images\/Screen_Shot_2022-06-01_at_9.58.05_am.png","social-video-link":"","social-video-pretitle":"","social-video-title":"Drea tries out The Skin Shark","social-video-author":"Drea"}},"94086b7e-01cc-4c7d-b6c1-668f093e4832":{"type":"social-videos","settings":{"social-video-image":"shopify:\/\/shop_images\/Screen_Shot_2022-04-01_at_12.21.49_pm.png","social-video-link":"https:\/\/vimeo.com\/695599077","social-video-pretitle":"THE SKIN SHARK","social-video-title":"How Zaruchinator uses The Skin Shark in her skin routine","social-video-author":"Laura"}},"a4e5f9d3-a0f9-4c5f-a695-8cf172d8c2ff":{"type":"social-videos","settings":{"social-video-image":"shopify:\/\/shop_images\/Screen_Shot_2022-04-01_at_12.34.25_pm.png","social-video-link":"https:\/\/vimeo.com\/700611919","social-video-pretitle":"The Skin Shark","social-video-title":"A day in the life of Sam Fricker & The Skin Shark","social-video-author":"Sam"}}},"block_order":["2d785077-4788-43fd-bc7a-7c13653e4ae8","70c92550-3879-470f-95e4-f6f1168e2187","d90ee8eb-88a0-41b3-b908-c420280a7212","870894ce-7b0c-4d36-aff6-52ac4ddee004","92168691-ffec-43bf-958d-40c27a47af4f","022560b9-c005-486c-ae22-154d51f9d254","1a8eb817-bfbb-4073-9e0f-9a5ad980ca10","25aeb6e6-c548-44b3-a173-d14f970911a5","71a3f523-5614-4533-b42a-3eed440d3fe5","ca97e3eb-d899-4613-a2c1-fdbfcf1e15bc","94086b7e-01cc-4c7d-b6c1-668f093e4832","a4e5f9d3-a0f9-4c5f-a695-8cf172d8c2ff"],"settings":{"title":"Tried. Tested. Loved","blog":"","blogType":"tiktok","button-label":"View All Videos"}},"1642031489f8296bef":{"type":"title-and-articles","disabled":true,"blocks":{"b424ed38-720f-494f-9ba6-e0251e22dd74":{"type":"social-videos","settings":{"social-video-link":"","social-video-pretitle":"","social-video-title":"","social-video-author":""}}},"block_order":["b424ed38-720f-494f-9ba6-e0251e22dd74"],"settings":{"title":"Watch more diaries","blog":"diaries","blogType":"diaries","button-label":"Watch more skin diaries"}}},"order":["skin-journeys-hero","1642039809721a7302","1642031489f8296bef"]}